simsusy/__init__.py
simsusy/__main__.py
simsusy/abs_calculator.py
simsusy/abs_model.py
simsusy/default_values.json
simsusy/mssm/__init__.py
simsusy/mssm/abstract.py
simsusy/mssm/input.py
simsusy/mssm/library.py
simsusy/mssm/mg5_tree_calculator.py
simsusy/mssm/model.py
simsusy/mssm/tanbeta_resum_calculator.py
simsusy/mssm/tree_calculator.py
simsusy/simsusy.py
simsusy/tests/__init__.py
simsusy/tests/mssm.slha
simsusy/tests/mssm.slha.in
simsusy/tests/mssm.slha2
simsusy/tests/mssm.slha2.in
simsusy/tests/outputs/mssm1.mg5_tree_calculator.v1
simsusy/tests/outputs/mssm1.mg5_tree_calculator.v2
simsusy/tests/outputs/mssm1.tree_calculator.v1
simsusy/tests/outputs/mssm1.tree_calculator.v2
simsusy/tests/outputs/mssm2.tree_calculator.v2
simsusy/tests/run.sh
simsusy/tests/sample.slha
simsusy/tests/test_abs_model.py
simsusy/tests/test_mssm_input.py
simsusy/tests/test_utility.py
simsusy/utility.py
simsusy-0.3.0.dist-info/entry_points.txt
simsusy-0.3.0.dist-info/LICENSE
simsusy-0.3.0.dist-info/WHEEL
simsusy-0.3.0.dist-info/METADATA
simsusy-0.3.0.dist-info/RECORD
