Metadata-Version: 2.1
Name: simsusy
Version: 0.3.0
Summary: A Python package for simple SUSY spectrum calculation
Home-page: https://github.com/misho104/simsusy
License: Apache 2.0
Author: Sho Iwamoto (Misho)
Author-email: webmaster@misho-web.com
Requires-Python: >=3.8,<4.0
Classifier: License :: Other/Proprietary License
Classifier: Programming Language :: Python :: 3
Classifier: Programming Language :: Python :: 3.10
Classifier: Programming Language :: Python :: 3.8
Classifier: Programming Language :: Python :: 3.9
Requires-Dist: click (>=8.1,<9.0)
Requires-Dist: colorama (>=0.4.4,<0.5.0)
Requires-Dist: coloredlogs (>=15.0,<16.0)
Requires-Dist: numpy (>=1.22,<2.0)
Requires-Dist: yaslha (>=0.3.3,<0.4.0)
Project-URL: Repository, https://github.com/misho104/simsusy
